LICENSE.txt
README.md
pyproject.toml
bitbucket_pipes_toolkit/__init__.py
bitbucket_pipes_toolkit/annotations.py
bitbucket_pipes_toolkit/core.py
bitbucket_pipes_toolkit/helpers.py
bitbucket_pipes_toolkit/test.py
bitbucket_pipes_toolkit.egg-info/PKG-INFO
bitbucket_pipes_toolkit.egg-info/SOURCES.txt
bitbucket_pipes_toolkit.egg-info/dependency_links.txt
bitbucket_pipes_toolkit.egg-info/requires.txt
bitbucket_pipes_toolkit.egg-info/top_level.txt