Metadata-Version: 2.2
Name: bitbucket-pipes-toolkit
Version: 6.1.1
Summary: This package contains various helpers for developing bitbucket pipelines pipes
Author-email: Atlassian <bitbucketci-team@atlassian.com>, bitbucketci-team@atlassian.com
Maintainer-email: Atlassian <bitbucketci-team@atlassian.com>
License: Copyright @ 2019 Atlassian Pty Ltd
Project-URL: Homepage, https://bitbucket.org/bitbucketpipelines/bitbucket-pipes-toolkit
Project-URL: Documentation, https://bitbucket-pipes-toolkit.readthedocs.io
Project-URL: Repository, https://bitbucket.org/bitbucketpipelines/bitbucket-pipes-toolkit
Project-URL: Issues, https://community.atlassian.com/t5/forums/postpage/board-id/bitbucket-pipelines-questions?add-tags=pipes,toolkit
Project-URL: Changelog, https://bitbucket.org/bitbucketpipelines/bitbucket-pipes-toolkit/src/master/CHANGELOG.md
Project-URL: Community, https://community.atlassian.com/t5/Bitbucket/ct-p/bitbucket
Keywords: bitbucket,bitbucket pipelines,bitbucket pipes,development
Classifier: Development Status :: 5 - Production/Stable
Classifier: Intended Audience :: Developers
Classifier: Topic :: Software Development :: Build Tools
Classifier: License :: OSI Approved :: Apache Software License
Classifier: Programming Language :: Python :: 3
Classifier: Programming Language :: Python :: 3.8
Classifier: Programming Language :: Python :: 3.9
Classifier: Programming Language :: Python :: 3.10
Classifier: Programming Language :: Python :: 3.11
Classifier: Programming Language :: Python :: 3.12
Classifier: Programming Language :: Python :: 3.13
Classifier: Programming Language :: Python :: 3 :: Only
Classifier: Topic :: Software Development :: Libraries
Requires-Python: >=3.8
License-File: LICENSE.txt
Requires-Dist: Cerberus==1.*
Requires-Dist: colorama==0.*
Requires-Dist: colorlog==6.*
Requires-Dist: docker==7.1.*
Requires-Dist: GitPython==3.*
Requires-Dist: requests~=2.32.4
Requires-Dist: PyYAML==6.*
Provides-Extra: tox
Requires-Dist: tox==4.*; extra == "tox"
Provides-Extra: testing
Requires-Dist: build==1.*; extra == "testing"
Requires-Dist: pytest==8.*; extra == "testing"
Requires-Dist: pytest-order==1.3.*; extra == "testing"
Requires-Dist: pytest-cov==5.*; extra == "testing"
Requires-Dist: pytest-doctestplus==1.*; extra == "testing"
Requires-Dist: pytest-mock==3.*; extra == "testing"
Provides-Extra: lint
Requires-Dist: flake8==7.*; extra == "lint"
Provides-Extra: coverage
Requires-Dist: coverage-badge==1.*; extra == "coverage"
Provides-Extra: docs
Requires-Dist: sphinx==8.*; extra == "docs"
